{
  "connection": "default",
  "collectionName": "renders",
  "info": {
    "name": "render",
    "description": "3d Rendering Designs"
  },
  "options": {
    "increments": true,
    "timestamps": [
      "created_at",
      "updated_at"
    ],
    "comment": ""
  },
  "attributes": {
    "title": {
      "type": "string",
      "required": true
    },
    "content": {
      "type": "text",
      "required": true
    },
    "image": {
      "model": "file",
      "via": "related",
      "plugin": "upload",
      "required": true
    }
  }
}